{
  "current_gate": "Phase 1 Complete",
  "gates": {
    "A": {
      "name": "Wallet Scaffold",
      "status": "completed",
      "started": "2025-09-30T11:01:08+05:30",
      "completed": "2025-09-30T11:16:50+05:30",
      "artifacts": [
        "Next.js app running on localhost:3000",
        "Phantom wallet connect/disconnect functional",
        "MAINNET badge visible in header",
        "Responsive landing page with hero and features",
        "Environment configuration complete"
      ]
    },
    "B": {
      "name": "Program Skeleton",
      "status": "completed",
      "started": "2025-09-30T11:29:38+05:30",
      "completed": "2025-09-30T11:40:24+05:30",
      "artifacts": [
        "Complete Anchor program (435 lines, compiles)",
        "IDL generated at web/app/_lib/idl.json",
        "Cargo check passes with warnings only",
        "All safety rails implemented",
        "Solana CLI v1.18.20 installed"
      ]
    },
    "C": {
      "name": "Create Flow",
      "status": "completed",
      "started": "2025-09-30T11:52:12+05:30",
      "completed": "2025-09-30T13:30:00+05:30",
      "artifacts": [
        "Create vault form with 4-step flow",
        "3 custom input components (Amount, Address, DateTime)",
        "Full client-side validation",
        "Review screen with warning",
        "Success confirmation",
        "Local storage integration",
        "Build successful (263 kB route)"
      ]
    },
    "D": {
      "name": "Dashboard & Detail",
      "status": "completed",
      "started": "2025-09-30T12:45:38+05:30",
      "completed": "2025-09-30T13:50:00+05:30",
      "artifacts": [
        "Vault list page with grid layout",
        "VaultCard component with status badges",
        "Countdown component (full and compact)",
        "StatusBadge component (locked/unlocked/released)",
        "Vault detail page with activity log",
        "Empty state and loading states",
        "Build successful (262 kB route)"
      ]
    },
    "E": {
      "name": "Release Flow",
      "status": "completed",
      "started": "2025-09-30T12:49:31+05:30",
      "completed": "2025-09-30T13:55:00+05:30",
      "artifacts": [
        "Release confirmation page",
        "4-step flow (Confirm → Processing → Success → Error)",
        "Solana Explorer links",
        "Transaction signature display",
        "Success screen with details",
        "Error handling with retry",
        "Build successful (262 kB route)"
      ]
    }
  },
  "last_updated": "2025-09-30T11:16:50+05:30"
}
